pnp/__init__.py
pnp/__main__.py
pnp/_constants.py
pnp/changelog.py
pnp/cli.py
pnp/github.py
pnp/gitutils.py
pnp/help_menu.py
pnp/py.typed
pnp/utils.py
pnp/handlers/__init__.py
pnp/handlers/giterr.py
push_n_publish-0.1.1.dist-info/licenses/LICENSE
push_n_publish-0.1.1.dist-info/METADATA
push_n_publish-0.1.1.dist-info/WHEEL
push_n_publish-0.1.1.dist-info/entry_points.txt
push_n_publish-0.1.1.dist-info/top_level.txt
push_n_publish-0.1.1.dist-info/RECORD
