Metadata-Version: 2.4
Name: push-n-publish
Version: 0.1.1
Summary: Push-and-publish: CLI tool to push commits, bump tags, and publish releases including GitHub releases.
Author-email: "Caleb M. Sibanda" <darkian.dev@gmail.com>
License: MIT
Project-URL: Homepage, https://github.com/2kDarki/pnp
Project-URL: Documentation, https://github.com/2kDarki/pnp#readme
Project-URL: Repository, https://github.com/2kDarki/pnp
Project-URL: Issues, https://github.com/2kDarki/pnp/issues
Keywords: git,automation,cli,release,devops,python
Classifier: Development Status :: 4 - Beta
Classifier: Environment :: Console
Classifier: Intended Audience :: Developers
Classifier: License :: OSI Approved :: MIT License
Classifier: Programming Language :: Python :: 3
Classifier: Programming Language :: Python :: 3.10
Classifier: Programming Language :: Python :: 3.11
Classifier: Programming Language :: Python :: 3.12
Classifier: Operating System :: OS Independent
Classifier: Topic :: Software Development :: Version Control :: Git
Requires-Python: >=3.10
License-File: LICENSE
Requires-Dist: requests>=2.30.0
Requires-Dist: tuikit>=0.1.2
Provides-Extra: dev
Requires-Dist: flake8; extra == "dev"
Requires-Dist: pytest; extra == "dev"
Requires-Dist: black; extra == "dev"
Requires-Dist: kitty; extra == "dev"
Requires-Dist: pylint; extra == "dev"
Dynamic: license-file
